rfxtrx/__init__.py
rfxtrx/_version.py
rfxtrx/mqtt_handler.py
rfxtrx/rfx_dump.py
rfxtrx/rfx_mqtt.py
rfxtrx/rfx_mqtt_pub.py
rfxtrx/rfx_mqtt_sub.py
rfxtrx/rfxtrx.py
rfxtrx_mqtt-0.0.0.dist-info/LICENSE
rfxtrx_mqtt-0.0.0.dist-info/METADATA
rfxtrx_mqtt-0.0.0.dist-info/WHEEL
rfxtrx_mqtt-0.0.0.dist-info/entry_points.txt
rfxtrx_mqtt-0.0.0.dist-info/top_level.txt
rfxtrx_mqtt-0.0.0.dist-info/RECORD
