Metadata-Version: 2.2
Name: rfxtrx-mqtt
Version: 0.0.0
Summary: A Python package for processing RFXtrx data with MQTT support and automation integration.
Author-email: Fredrik Blix <fredrik.blix@gmail.com>
License: MIT
Project-URL: Homepage, https://github.com/FredrikBlix/rfxtrx-mqtt
Project-URL: Repository, https://github.com/FredrikBlix/rfxtrx-mqtt
Project-URL: Issues, https://github.com/FredrikBlix/rfxtrx-mqtt/issues
Requires-Python: >=3.6
License-File: LICENSE
Requires-Dist: pyserial
Requires-Dist: paho-mqtt
